weni/feature_flags/__init__.py
weni/feature_flags/apps.py
weni/feature_flags/authentication.py
weni/feature_flags/conftest.py
weni/feature_flags/converters.py
weni/feature_flags/integrations/__init__.py
weni/feature_flags/integrations/growthbook/__init__.py
weni/feature_flags/integrations/growthbook/clients.py
weni/feature_flags/migrations/0001_initial.py
weni/feature_flags/migrations/__init__.py
weni/feature_flags/models.py
weni/feature_flags/services.py
weni/feature_flags/settings.py
weni/feature_flags/shortcuts.py
weni/feature_flags/tasks.py
weni/feature_flags/tests/__init__.py
weni/feature_flags/tests/test_authentication.py
weni/feature_flags/tests/test_converters.py
weni/feature_flags/tests/test_services.py
weni/feature_flags/tests/test_shortcuts.py
weni/feature_flags/tests/test_tasks.py
weni/feature_flags/tests/test_validators.py
weni/feature_flags/tests/test_views.py
weni/feature_flags/validators.py
weni/feature_flags/views.py
weni_feature_flags-2.1.2.dist-info/LICENSE
weni_feature_flags-2.1.2.dist-info/METADATA
weni_feature_flags-2.1.2.dist-info/WHEEL
weni_feature_flags-2.1.2.dist-info/RECORD
