Metadata-Version: 2.1
Name: weni-feature-flags
Version: 2.1.2
Summary: Weni's feature flags SDK for Python backends
Author: Kallil Souza dos Santos
Author-email: kallilsouza@hotmail.com
Requires-Python: >=3.8,<4.0
Classifier: Programming Language :: Python :: 3
Classifier: Programming Language :: Python :: 3.8
Classifier: Programming Language :: Python :: 3.9
Classifier: Programming Language :: Python :: 3.10
Classifier: Programming Language :: Python :: 3.11
Classifier: Programming Language :: Python :: 3.12
Classifier: Programming Language :: Python :: 3.13
Requires-Dist: celery (>=5.0.0,<6.0)
Requires-Dist: django (>=3.2.22,<6.0)
Requires-Dist: django-redis (>=4.0.0,<=6.0)
Requires-Dist: djangorestframework (>=3.12.0,<4.0)
Requires-Dist: growthbook (>=1.0.0,<2.0)
Requires-Dist: requests (>=2.25.0,<3.0)
